vexy_overnight/__init__.py
vexy_overnight/__version__.py
vexy_overnight/cli.py
vexy_overnight/config.py
vexy_overnight/hook_runtime.py
vexy_overnight/hooks.py
vexy_overnight/launchers.py
vexy_overnight/py.typed
vexy_overnight/rules.py
vexy_overnight/session_state.py
vexy_overnight/updater.py
vexy_overnight/user_settings.py
vexy_overnight/vexy_overnight.py
vexy_overnight/hooks_tpl/__init__.py
vexy_overnight/hooks_tpl/vocl_go.py
vexy_overnight/hooks_tpl/vocl_new.py
vexy_overnight/hooks_tpl/voco_go.py
vexy_overnight/hooks_tpl/voco_new.py
vexy_overnight/hooks_tpl/voge_go.py
vexy_overnight/tools/__init__.py
vexy_overnight/tools/version_bump.py
vexy_overnight-1.1.2.dist-info/METADATA
vexy_overnight-1.1.2.dist-info/WHEEL
vexy_overnight-1.1.2.dist-info/entry_points.txt
vexy_overnight-1.1.2.dist-info/licenses/LICENSE
vexy_overnight-1.1.2.dist-info/RECORD
